Metadata-Version: 2.1
Name: discordies
Version: 0.1.1
Summary: discordies
Home-page: https://github.com/amorgan/discordies
Author: Nicholas King
Author-email: amorgan@martin.info
License: MIT
Platform: UNKNOWN
Requires-Python: >=3.6
